[
    {
    "iconUrl": "https://midasxxi.com/wp-content/uploads/2024/01/cropped-favicon.png",
    "apiVersion": 1,
    "repositoryUrl": "https://github.com/sad25kag/BetbetMiro-Extension",
    "fileSize": 21789,
    "status": 1,
    "language": "id",
    "authors": ["BetbetMiro"],
    "tvTypes": ["AsianDrama", "TvSeries", "Movie"],
    "version": 1,
    "internalName": "MidasXXi",
    "description": "📺 Streaming Movie and TV Series",
    "url": "https://raw.githubusercontent.com/sad25kag/BetbetMiro-Extension/master/Betbet/MidasXXi.cs3",
    "name": "MidasXXi"
  },
  {
    "iconUrl": "https://eskipii.com/wp-content/uploads/2023/10/favicon.png",
    "apiVersion": 1,
    "repositoryUrl": "https://github.com/sad25kag/BetbetMiro-Extension",
    "fileSize": 21830,
    "status": 1,
    "language": "id",
    "authors": ["BetbetMiro"],
    "tvTypes": ["AsianDrama", "TvSeries", "Movie"],
    "version": 1,
    "internalName": "Pusatmovie",
    "description": "📺 Streaming Movie and TV Series",
    "url": "https://raw.githubusercontent.com/sad25kag/BetbetMiro-Extension/master/Betbet/Pusatmovie.cs3",
    "name": "Pusatmovie"
  },
  {
    "iconUrl": "https://savefilm21.info/favicon.png",
    "apiVersion": 1,
    "repositoryUrl": "https://github.com/sad25kag/BetbetMiro-Extension",
    "fileSize": 21860,
    "status": 1,
    "language": "id",
    "authors": ["BetbetMiro"],
    "tvTypes": ["AsianDrama", "TvSeries", "Movie"],
    "version": 1,
    "internalName": "Savefilm",
    "description": "📺 Streaming Movie and TV Series",
    "url": "https://raw.githubusercontent.com/sad25kag/BetbetMiro-Extension/master/Betbet/Savefilm.cs3",
    "name": "Savefilm"
  },
  {
    "iconUrl": "https://i.ibb.co.com/YFbP1FSr/icon.png",
    "apiVersion": 1,
    "repositoryUrl": "https://github.com/sad25kag/BetbetMiro-Extension",
    "fileSize": 74677,
    "status": 1,
    "language": "id",
    "authors": ["BetbetMiro"],
    "tvTypes": ["TvSeries", "Movie", "Anime", "AsianDrama"],
    "version": 1,
    "internalName": "Moviebox",
    "description": "📺 Moviebox - Netnaija - Sflix",
    "url": "https://raw.githubusercontent.com/sad25kag/BetbetMiro-Extension/master/Betbet/Moviebox.cs3",
    "name": "Moviebox"
  },
  {
        "url": "https://raw.githubusercontent.com/sad25kag/BetbetMiro-Extension/master/Betbet/MoonTV.cs3",
        "status": 1,
        "version": 4,
        "name": "MoonTV",
        "internalName": "MoonTV",
        "authors": [
            "BetbetMiro"
        ],
        "description": "Movies & TV Series Etc Settings allow selecting domains such as 123cine,Flixzone etc",
        "fileSize": 65352,
        "repositoryUrl": "https://github.com/sad25kag/BetbetMiro-Extension",
        "language": "en",
        "tvTypes": [
            "AsianDrama",
            "TvSeries",
            "Anime",
            "Movie",
            "Cartoon",
            "AnimeMovie"
        ],
        "iconUrl": "https://www.google.com/s2/favicons?domain=moontv.to/&sz=%size%",
        "apiVersion": 1,
        "fileHash": "sha256-af29b2010107ce2b162f1756fce80b71cff4b64e099b5d1920b6fc3a192bdb7e"
    }
]